crypterma
