Metadata-Version: 2.1
Name: crypterma
Version: 0.1.9
Summary: ASCII-chart version of how Bitcoin grows
Home-page: https://github.com/gabolaev/crypterma
Author: George Gabolaev
Author-email: gabolaev98@gmail.com
License: MIT
Platform: UNKNOWN
Requires-Python: >=3.6
